pshelf/__init__.py
pshelf/alternatives.py
pshelf/cleanup.py
pshelf/shell.py
pshelf/userInput.py
pshelf-0.5.dist-info/DESCRIPTION.rst
pshelf-0.5.dist-info/METADATA
pshelf-0.5.dist-info/RECORD
pshelf-0.5.dist-info/WHEEL
pshelf-0.5.dist-info/entry_points.txt
pshelf-0.5.dist-info/metadata.json
pshelf-0.5.dist-info/top_level.txt
